[
    [
        {
            "Content": "這問題無解了",
            "Vote": "推",
            "User": "kshs920742"
        },
        {
            "Content": "愛是信任而不是限制，只能說你們價值觀不同",
            "Vote": "推",
            "User": "Athens"
        },
        {
            "Content": "會喝酒嗎??",
            "Vote": "→",
            "User": "zippy"
        },
        {
            "Content": "看相處情況而定",
            "Vote": "推",
            "User": "kidd232"
        },
        {
            "Content": "我覺得吃比男友重要欸哈哈哈哈",
            "Vote": "推",
            "User": "Jger"
        }
    ],
    [
        {
            "Content": "嘲諷他考不上說要分手要是男的有出息發奮考上會感謝妳",
            "Vote": "推",
            "User": "neverlight"
        },
        {
            "Content": "但男的大受打擊考不上就會恨妳",
            "Vote": "→",
            "User": "neverlight"
        },
        {
            "Content": "然後要是認真要考試的壓力真的很大",
            "Vote": "推",
            "User": "neverlight"
        },
        {
            "Content": "曾經也是有一直鼓勵要考研究所和檢定考的對象",
            "Vote": "推",
            "User": "neverlight"
        },
        {
            "Content": "兩個人真的很都辛苦 看你受不受的了嘍",
            "Vote": "→",
            "User": "neverlight"
        },
        {
            "Content": "你都知道他很脆弱了還想分手...",
            "Vote": "→",
            "User": "westgatepark"
        },
        {
            "Content": "曾經有學長考試前晚收到錯簡訊 記恨到現在 也有分手",
            "Vote": "推",
            "User": "neverlight"
        },
        {
            "Content": "後同學發誓要成功給狗男女看（因為是劈腿）然後衝事業",
            "Vote": "→",
            "User": "neverlight"
        },
        {
            "Content": "不過總之重要時刻分手都會被討厭啦ˊ_>ˋ",
            "Vote": "→",
            "User": "neverlight"
        },
        {
            "Content": "你不應該覺得他懦弱 而是要更加的鼓勵他吧.....",
            "Vote": "→",
            "User": "wincecarter"
        },
        {
            "Content": "要是看到身邊有能力強的異性相比之下就",
            "Vote": "→",
            "User": "neverlight"
        },
        {
            "Content": "既然這麼想分就不要怕他恨你啊",
            "Vote": "推",
            "User": "miketsai45"
        },
        {
            "Content": "不要怕當懷人 如果是七月那個考試 現在分還有幾個月可以療傷",
            "Vote": "推",
            "User": "yshin"
        },
        {
            "Content": "最糟糕的就是選擇別人考試的時候提分手",
            "Vote": "噓",
            "User": "diefishfish"
        },
        {
            "Content": "現在不提 就要有把握不會到考試前一兩個月才提喔",
            "Vote": "→",
            "User": "yshin"
        },
        {
            "Content": "想分手,但有那麼急嗎？",
            "Vote": "→",
            "User": "acetoluene"
        },
        {
            "Content": "要分就快分，難道他這次考完就沒機會考了嗎?",
            "Vote": "→",
            "User": "AAAdolph"
        },
        {
            "Content": "可以啊為啥不可以 又不是簽契約=.=",
            "Vote": "推",
            "User": "gr1031"
        },
        {
            "Content": "遠距就拖到等他考上在講，反正你們也很少見面吧？",
            "Vote": "推",
            "User": "hotqiqi"
        },
        {
            "Content": "那萬一對方一直沒考上 要拖到哪時~ 妳不愛他了就分吧",
            "Vote": "→",
            "User": "suleyman"
        },
        {
            "Content": "但是他恨妳大概是避免不了的...",
            "Vote": "→",
            "User": "suleyman"
        },
        {
            "Content": "談感情到了分手時，真辛苦",
            "Vote": "推",
            "User": "yule1224"
        },
        {
            "Content": "考完but放榜前是最好的時間了~~",
            "Vote": "推",
            "User": "yniori"
        },
        {
            "Content": "拜託考完再說 會害死人",
            "Vote": "噓",
            "User": "nikemj23"
        },
        {
            "Content": "不要他考上你又貼回去就好",
            "Vote": "→",
            "User": "steven211"
        },
        {
            "Content": "當然能阿 只是看你要不要考慮對方的處境而已",
            "Vote": "→",
            "User": "XLnaki"
        },
        {
            "Content": "其實妳只是不愛他了 跟遠距離沒什麼太大的關聯 還愛",
            "Vote": "推",
            "User": "thepolarstar"
        },
        {
            "Content": "著 就算生活圈不同 也會想跟對方分享自己的遇到的人",
            "Vote": "→",
            "User": "thepolarstar"
        },
        {
            "Content": "事物 所以不用替自己找一堆理由或藉口 說服自己",
            "Vote": "→",
            "User": "thepolarstar"
        },
        {
            "Content": "這樣反而看了會討厭",
            "Vote": "→",
            "User": "thepolarstar"
        },
        {
            "Content": "你的生活不需要他了 就這樣",
            "Vote": "推",
            "User": "musha1989"
        },
        {
            "Content": "考試中可以講話嗎? 不要影響他人作答",
            "Vote": "噓",
            "User": "caesar0926"
        },
        {
            "Content": "妳自己都知道他是信任妳才跟妳透露那些 但妳卻嫌他弱還想",
            "Vote": "噓",
            "User": "asbrian"
        },
        {
            "Content": "跟他分手? 這...",
            "Vote": "→",
            "User": "asbrian"
        },
        {
            "Content": "妳自己都知道他是信任妳才跟妳透露那些 但妳卻嫌他弱還想",
            "Vote": "噓",
            "User": "kimade"
        },
        {
            "Content": "跟他分手? 早知道你是這種人 他也可以裝做自己很強啊",
            "Vote": "→",
            "User": "kimade"
        },
        {
            "Content": "不要消費人家對你的信任",
            "Vote": "→",
            "User": "kimade"
        },
        {
            "Content": "女生好奇怪阿，我跟你男友相反，為了怕被看雖，很少和女友",
            "Vote": "噓",
            "User": "losage"
        },
        {
            "Content": "提到我脆弱的部分，反而被前女友以此為藉口提分手，怪哉",
            "Vote": "→",
            "User": "losage"
        },
        {
            "Content": "幹這種最基掰",
            "Vote": "噓",
            "User": "nicholas8855"
        }
    ],
    [
        {
            "Content": "我覺得不敢打擾根本是藉口耶~就我來看~",
            "Vote": "推",
            "User": "lubemyself"
        },
        {
            "Content": "這時候就是要衝下去一趟好好安慰他~就算沒時間~",
            "Vote": "→",
            "User": "lubemyself"
        },
        {
            "Content": "電話也該好好安慰~而不是避重就輕~",
            "Vote": "→",
            "User": "lubemyself"
        },
        {
            "Content": "應該要立刻飛奔到她身邊,就算什麼都說不出來,陪在身邊就對了",
            "Vote": "→",
            "User": "ankaa"
        },
        {
            "Content": "你傻啦 這時候最該多陪伴安慰關心了",
            "Vote": "推",
            "User": "kidd232"
        }
    ],
    [
        {
            "Content": "如果真的不想分開 和男友好好討論一下未來規劃吧",
            "Vote": "推",
            "User": "ferrule"
        },
        {
            "Content": "工作後各自給爸媽孝親費很正常 但也要留能生活的錢下來",
            "Vote": "→",
            "User": "ferrule"
        },
        {
            "Content": "聽起來男友媽媽比較容易\"花太多錢\" 這點需要男友去處理",
            "Vote": "→",
            "User": "ferrule"
        },
        {
            "Content": "好比固定孝親費金額 +年節紅包 其他時候再多要也不要給",
            "Vote": "→",
            "User": "ferrule"
        },
        {
            "Content": "建議男友和妹妹商量好金額  爸媽的錢分開給比較恰當",
            "Vote": "→",
            "User": "ferrule"
        },
        {
            "Content": "請問「soul mate」是什麼意思啊",
            "Vote": "→",
            "User": "diess"
        },
        {
            "Content": "先合緩一下情緒  一起討論吧  個人覺給錢其實是最容易的",
            "Vote": "→",
            "User": "ferrule"
        },
        {
            "Content": "hey soul sister, dont want to miss a single thing",
            "Vote": "→",
            "User": "RachelMcAdam"
        },
        {
            "Content": "我查過網路的法律問答，給予父母不用抽稅的金額最高是110萬",
            "Vote": "→",
            "User": "diess"
        },
        {
            "Content": "每一年，不過若不方便不需要付那麼高的金額",
            "Vote": "→",
            "User": "diess"
        },
        {
            "Content": "只要付夠一般生活的奉養費就好，奢侈品跟養大自己的金錢",
            "Vote": "→",
            "User": "diess"
        },
        {
            "Content": "是兩碼子的事情，要自己能力有多餘的才能幫助父母奢侈品費用",
            "Vote": "→",
            "User": "diess"
        },
        {
            "Content": "沒有多餘的能力還要扛起來，這跟打腫臉充胖子差不多",
            "Vote": "→",
            "User": "diess"
        },
        {
            "Content": "有這種心態的人不要也罷",
            "Vote": "→",
            "User": "diess"
        },
        {
            "Content": "男友和妹妹商妥要給父母多少孝親費，再多就沒有，以防亂",
            "Vote": "推",
            "User": "niceling"
        },
        {
            "Content": "花後才找兒女要吧…",
            "Vote": "→",
            "User": "niceling"
        },
        {
            "Content": "就算妳很會賺=>變成行動ATM，要是妳不賺=>就是負債窮忙",
            "Vote": "推",
            "User": "post91"
        },
        {
            "Content": "到最後沒有自己的生活品質",
            "Vote": "→",
            "User": "post91"
        },
        {
            "Content": "妳確定妳的未來要過這樣的生活?",
            "Vote": "→",
            "User": "post91"
        },
        {
            "Content": "確實是誰想嫁入他們家就算那個人倒楣",
            "Vote": "→",
            "User": "AppleAlice"
        },
        {
            "Content": "妳可以參考婚姻版17791篇,或許會幫助妳釐清一些頭緒",
            "Vote": "推",
            "User": "ayaneyuri"
        },
        {
            "Content": "diess:沒有多餘的能力還要扛起來，這跟打腫臉充胖子差不多",
            "Vote": "推",
            "User": "gr1031"
        },
        {
            "Content": "他在逞強而已 照他爸媽這鬼樣子 我不信他撐得住",
            "Vote": "→",
            "User": "gr1031"
        },
        {
            "Content": "婚姻是兩個家庭的事情 除非你男友跟他父母斷開 不然沒轍",
            "Vote": "→",
            "User": "gr1031"
        },
        {
            "Content": "但照你男友的說詞看來 我覺得 應該是沒什麼希望ˊ_>ˋ",
            "Vote": "推",
            "User": "gr1031"
        },
        {
            "Content": "你男友愚孝不設停損點，你也要跟著陪葬嗎?",
            "Vote": "推",
            "User": "linyap"
        },
        {
            "Content": "D大 說的110萬是誤解喔!撫養一個人的扣除額只有七萬多",
            "Vote": "推",
            "User": "particular"
        },
        {
            "Content": "110萬是父母被贈與不用繳稅  超過要繳稅",
            "Vote": "→",
            "User": "particular"
        },
        {
            "Content": "記得以後結婚不要生小孩。浪費錢又浪費時間。",
            "Vote": "噓",
            "User": "dos771215"
        },
        {
            "Content": "我覺得他爸媽對於媳婦的想法很務實",
            "Vote": "→",
            "User": "Dvallina"
        },
        {
            "Content": "每餐50元～請注意一下難有的健康..",
            "Vote": "推",
            "User": "MaiLu"
        },
        {
            "Content": "把媽媽卡剪掉 ...",
            "Vote": "噓",
            "User": "henry12"
        },
        {
            "Content": "確實是誰想嫁入他們家就算那個人倒楣+1",
            "Vote": "推",
            "User": "moki"
        },
        {
            "Content": "真的愛到分不開就一直談戀愛吧 等年紀到了你會知道方向",
            "Vote": "推",
            "User": "amida959"
        },
        {
            "Content": "但是真的不要想結婚 這種情況除非妳革命家裡不會讓妳嫁的",
            "Vote": "→",
            "User": "amida959"
        },
        {
            "Content": "1兩人都還沒出社會，出了社會看法想法都會有差。",
            "Vote": "推",
            "User": "kerner"
        },
        {
            "Content": "屆時再來談婚姻吧！",
            "Vote": "→",
            "User": "kerner"
        },
        {
            "Content": "妳結婚後才是真正痛苦的開始  現在長痛不如短痛",
            "Vote": "推",
            "User": "white75724"
        }
    ],
    [
        {
            "Content": "照三餐的簡訊和一顆願意等待他的心喽!",
            "Vote": "推",
            "User": "helloman29"
        },
        {
            "Content": "不兵變.不抱怨.用心安排下次回台灣的約會",
            "Vote": "→",
            "User": "m6dj942k7"
        },
        {
            "Content": "不兵變大過一切",
            "Vote": "推",
            "User": "RachelMcAdam"
        },
        {
            "Content": "差點以為你是我弟的女友!不過你男友當好久喔!快2年??",
            "Vote": "→",
            "User": "CHRISTINAYEN"
        },
        {
            "Content": "我當時給我男友寄了他愛吃的東西,他就很開心了~XD",
            "Vote": "推",
            "User": "fangru"
        },
        {
            "Content": "應該是今年十月吧...",
            "Vote": "推",
            "User": "accu0989"
        },
        {
            "Content": "耐心聽他說話，但是我是他退伍後說不要我...所以過好自",
            "Vote": "推",
            "User": "funnychia"
        },
        {
            "Content": "真的試著撒嬌，還有讓他放心就夠了",
            "Vote": "推",
            "User": "tokio01248"
        },
        {
            "Content": "現在外島比本島好很多 寫寫信會是一個蠻不錯的心靈慰藉",
            "Vote": "→",
            "User": "wildkidy"
        },
        {
            "Content": "可以去站崗板看看喔!!!應該有不錯的意見!^^",
            "Vote": "推",
            "User": "opens"
        },
        {
            "Content": "外島比本島好很多  聽你放屁",
            "Vote": "推",
            "User": "yozeng"
        },
        {
            "Content": "外島怎麼樣都比本島賽好嗎",
            "Vote": "推",
            "User": "MrTen"
        },
        {
            "Content": "真的要看單位和運氣  我也遇過外島爽翻天的人",
            "Vote": "→",
            "User": "steven211"
        },
        {
            "Content": "這裡不是軍旅版 但我還是想說本島就算累但至少十幾天可以",
            "Vote": "推",
            "User": "MrTen"
        },
        {
            "Content": "回陽間紓壓一下 外島假就被島休扣掉一半 那島休在幹嘛",
            "Vote": "→",
            "User": "MrTen"
        },
        {
            "Content": "穿著軍服打網咖若你喜歡打LOL也許還不錯 可是至少要2-3個月",
            "Vote": "→",
            "User": "MrTen"
        },
        {
            "Content": "才能還陽 外島還好外離島更慘如果指揮部又很黑 督導還是會來",
            "Vote": "→",
            "User": "MrTen"
        },
        {
            "Content": "光放假就少人家一大半，外島就是賽",
            "Vote": "→",
            "User": "bluewindwmg"
        },
        {
            "Content": "我在外島當兵真的很爽爽到靠杯 又有親戚家可以跑",
            "Vote": "推",
            "User": "SeaNMiz"
        },
        {
            "Content": "無聊就打電話給他 寫信也很不錯因為現在很少寫了",
            "Vote": "→",
            "User": "SeaNMiz"
        },
        {
            "Content": "特別節日寄個卡片明信片 會就感心",
            "Vote": "→",
            "User": "SeaNMiz"
        },
        {
            "Content": "如果在莒光可以寄一堆零食因為沒有7-11另外那邊很冷",
            "Vote": "推",
            "User": "barbie0924"
        },
        {
            "Content": "暖暖包,保溫杯,沖泡包,厚襪子,圍巾(睡覺用)也都可以寄",
            "Vote": "→",
            "User": "barbie0924"
        },
        {
            "Content": "因為一天內電話可能不超過5通沒辦法講很久,平常可以寫",
            "Vote": "→",
            "User": "barbie0924"
        },
        {
            "Content": "日記,累積很多篇再一次寄給他看",
            "Vote": "→",
            "User": "barbie0924"
        },
        {
            "Content": "然後可以寄耳麥給他,島休去網咖可以視訊",
            "Vote": "→",
            "User": "barbie0924"
        },
        {
            "Content": "信+1 當兵在外島 那時沒女友 收到朋友的信就很感動了",
            "Vote": "推",
            "User": "deenband"
        },
        {
            "Content": "去站崗板 裡面的女生有超級豐富的經驗!!",
            "Vote": "→",
            "User": "summeruse"
        },
        {
            "Content": "寄什麼物品都寫一大堆分享給板友 很用心!",
            "Vote": "→",
            "User": "summeruse"
        }
    ],
    [
        {
            "Content": "不會~有人要開車載我我可是超開心的阿!",
            "Vote": "推",
            "User": "fenix910"
        },
        {
            "Content": "我不會主動說要開車載男生出去，除非對方提到車的需求耶",
            "Vote": "→",
            "User": "azasibyl"
        },
        {
            "Content": "我弟女友有車，我弟沒有，且車都女生開，沒問題啊！",
            "Vote": "→",
            "User": "yc11"
        },
        {
            "Content": "因為機車比較“貼”近",
            "Vote": "推",
            "User": "kakoiee"
        },
        {
            "Content": "不過我男朋友似乎不太介意，之前都開我的車開爽爽XD",
            "Vote": "→",
            "User": "azasibyl"
        },
        {
            "Content": "男的沒車坐女生的車=沒面子",
            "Vote": "推",
            "User": "neverlight"
        },
        {
            "Content": "補充！！！是對有些男的來說！！！非全部",
            "Vote": "→",
            "User": "neverlight"
        },
        {
            "Content": "可能會覺得自己買不起車比妳弱有自卑感",
            "Vote": "推",
            "User": "neverlight"
        },
        {
            "Content": "我會想自己開比較安全XD",
            "Vote": "推",
            "User": "TQTa"
        },
        {
            "Content": "或怕被別的男的笑說沒用要坐女生的車",
            "Vote": "→",
            "User": "neverlight"
        },
        {
            "Content": "若是同年齡男性 有念大學當完兵出社會不久 沒啥成就",
            "Vote": "推",
            "User": "neverlight"
        },
        {
            "Content": "也許有的男生會覺得，主動說自己有車可以開，有間接炫耀",
            "Vote": "→",
            "User": "azasibyl"
        },
        {
            "Content": "不喜歡的男是自卑吧",
            "Vote": "推",
            "User": "newsoulth"
        },
        {
            "Content": "1經濟能力和自信都還很弱小 所以有些人會這樣可以理解",
            "Vote": "推",
            "User": "neverlight"
        },
        {
            "Content": "我是男生 我會超開心XD",
            "Vote": "推",
            "User": "wincecarter"
        },
        {
            "Content": "我是男生 我會超開心 但前提是技術要好",
            "Vote": "→",
            "User": "eva19452002"
        },
        {
            "Content": "根據我經驗確實不太好，不完全是因為男生會自卑還有很多",
            "Vote": "推",
            "User": "Softrella"
        },
        {
            "Content": "我很怕給女人載，技術是一回事，care的是臨場反應，後來乾",
            "Vote": "推",
            "User": "shango"
        },
        {
            "Content": "練恥力是被載去車旅",
            "Vote": "推",
            "User": "Berith"
        },
        {
            "Content": "脆自己開算了。開車並不是讓車前進後退而已，就像料理並不",
            "Vote": "→",
            "User": "shango"
        },
        {
            "Content": "不是只是把食物弄熱可以吃就好",
            "Vote": "→",
            "User": "shango"
        },
        {
            "Content": "你不放心，說不定對方更不放心　XD",
            "Vote": "→",
            "User": "shango"
        },
        {
            "Content": "看年紀 以前的我會覺得不行 現在的我超開心!",
            "Vote": "推",
            "User": "akmc"
        },
        {
            "Content": "因為男生愛面子,女生開車會覺得自己有點廢,我是沒差啦",
            "Vote": "→",
            "User": "knml"
        },
        {
            "Content": "不願or不敢給女生載的男生格局太小 放掉也不可惜啦 (拍)",
            "Vote": "推",
            "User": "azure1428"
        },
        {
            "Content": "我會有點自卑耶，但不會表現出來就是了，就乖乖的給人家載",
            "Vote": "推",
            "User": "abcdef5"
        },
        {
            "Content": "也不會主動問說要不要我開，不過停車時會問要不要我來停",
            "Vote": "→",
            "User": "abcdef5"
        },
        {
            "Content": "我曾經有男生說 因為我有車而不敢追我的就是了 生氣:(",
            "Vote": "推",
            "User": "temere"
        },
        {
            "Content": "弱就算了還自卑 這種男的不要也罷",
            "Vote": "推",
            "User": "fatalsecret"
        },
        {
            "Content": "曾坐過女生開車，對方名言：過彎不是要加速嗎？",
            "Vote": "推",
            "User": "Dvc"
        },
        {
            "Content": "哈  這種男人格局真的很小",
            "Vote": "推",
            "User": "summeruse"
        },
        {
            "Content": "他沒車你還敢讓他開喔 愛惜自己的車吧~~",
            "Vote": "→",
            "User": "summeruse"
        },
        {
            "Content": "shango無聊的性別歧視言論",
            "Vote": "噓",
            "User": "LebronKing"
        },
        {
            "Content": "有性別歧視的人可以直接跳過了 先幫你篩選掉那些最差的",
            "Vote": "→",
            "User": "Skabo"
        },
        {
            "Content": "對性別開車有刻板印象真的是..",
            "Vote": "推",
            "User": "neverlight"
        },
        {
            "Content": "格局小的放掉也不可惜+1",
            "Vote": "推",
            "User": "yiro"
        },
        {
            "Content": "現在的價值觀導致男性對這種狀況會有點自卑吧",
            "Vote": "推",
            "User": "endlessgreen"
        },
        {
            "Content": "我很怕給男生載，當然也不喜歡我的車給男生開",
            "Vote": "推",
            "User": "huuban"
        },
        {
            "Content": "我姊年紀跟你差不多 也有車 也載男生ok的",
            "Vote": "推",
            "User": "tiny5566"
        },
        {
            "Content": "弱者總是愛面子",
            "Vote": "推",
            "User": "momomom"
        },
        {
            "Content": "車是你的當然不能給別人開,出事的話責任歸屬很麻煩",
            "Vote": "推",
            "User": "tsming"
        },
        {
            "Content": "我好想給你載喔！",
            "Vote": "推",
            "User": "hotanger"
        },
        {
            "Content": "過彎不是要加速嗎XDDDDD",
            "Vote": "推",
            "User": "tsming"
        },
        {
            "Content": "不介意+1 有人載超開心的=v=",
            "Vote": "推",
            "User": "goldseed"
        },
        {
            "Content": "根據我經驗也是好像有的人會慢慢的氣弱下去..除非對方也開車",
            "Vote": "推",
            "User": "peda"
        },
        {
            "Content": "我想問 我男的 因為生理上的問題 不能開車 這樣呢?",
            "Vote": "推",
            "User": "bill0205"
        },
        {
            "Content": "我願意給你載 ._./",
            "Vote": "推",
            "User": "Neurontin"
        },
        {
            "Content": "不會啊 我考照前一直給我姊載 也不會覺得怎樣啊",
            "Vote": "推",
            "User": "gohome0083"
        },
        {
            "Content": "順路的話可以載我 XD",
            "Vote": "→",
            "User": "gohome0083"
        },
        {
            "Content": "對方可能是怕你的開車技術吧XDD",
            "Vote": "→",
            "User": "cvsugar"
        },
        {
            "Content": "當我知道我是路痴而且女友開車技術比我好時，現在我都在副座",
            "Vote": "→",
            "User": "carey"
        },
        {
            "Content": "不過當她握起方向盤時，平常的小貓咪立刻變身成母老虎...",
            "Vote": "→",
            "User": "carey"
        },
        {
            "Content": "我20歲就開車了,遇過的男生不管自己有無四輪都願意讓",
            "Vote": "→",
            "User": "ShiningRuby"
        },
        {
            "Content": "有被女生朋友載過  感覺蠻特別的",
            "Vote": "推",
            "User": "vinsanity25"
        },
        {
            "Content": "車應該不要讓別人開吧？我家連家人都不行",
            "Vote": "推",
            "User": "Gunish"
        },
        {
            "Content": "萬一出事保險理賠的責任根本就算不清",
            "Vote": "→",
            "User": "Gunish"
        },
        {
            "Content": "那些男人都太弱了 就這樣",
            "Vote": "→",
            "User": "triptane"
        },
        {
            "Content": "我巴不得每天都有女生載我出去玩,超有面子的~~~",
            "Vote": "推",
            "User": "memoryfarm"
        },
        {
            "Content": "這也太玻璃心了吧?!我平常都開我的車載我老公啊!",
            "Vote": "推",
            "User": "CHRISTINAYEN"
        },
        {
            "Content": "女生有車超爽的咧",
            "Vote": "推",
            "User": "scpx"
        },
        {
            "Content": "會自卑+1 這也是對自我的要求吧",
            "Vote": "推",
            "User": "hanopl"
        },
        {
            "Content": "有些人會有壓力  有些人就不會囉",
            "Vote": "→",
            "User": "cdcardabc"
        },
        {
            "Content": "載我出去玩吧>///<",
            "Vote": "推",
            "User": "kidd232"
        },
        {
            "Content": "fenix910:不會~有人要開車載我我可是超開心的阿!",
            "Vote": "→",
            "User": "TREKKER"
        },
        {
            "Content": "都什麼時代了.....有些女生開車技術很好阿!!",
            "Vote": "推",
            "User": "zeemaneffect"
        },
        {
            "Content": "完全不會  女生開車也很好啊",
            "Vote": "推",
            "User": "gogoangelin"
        },
        {
            "Content": "放心，一定會有問題，男人是有自尊的",
            "Vote": "→",
            "User": "inking"
        },
        {
            "Content": "差不多年齡的女生有車還可以載他，和給女友或姊姊載根本不",
            "Vote": "→",
            "User": "inking"
        },
        {
            "Content": "不然就是多少心裡不信任妳的開車能力",
            "Vote": "→",
            "User": "inking"
        },
        {
            "Content": "女生有四輪很好! 行動自由 尤其結婚之後 XD",
            "Vote": "推",
            "User": "square514"
        },
        {
            "Content": "不敢坐女生開的車，就自己買一台，不要戰女生技術差",
            "Vote": "推",
            "User": "youyu0914"
        },
        {
            "Content": "給人載多爽阿!",
            "Vote": "推",
            "User": "inuwanwan"
        },
        {
            "Content": "完全不會介意，請載我出去玩!!!",
            "Vote": "推",
            "User": "yuiop0929"
        },
        {
            "Content": "自卑是一回事，但也包含了男性對自己的期許吧",
            "Vote": "推",
            "User": "seaman675"
        },
        {
            "Content": "超爽的有車子坐～   我覺得講好就沒差了吧",
            "Vote": "推",
            "User": "peardog"
        },
        {
            "Content": "我前女友也是有自己的車，而我沒車 說真的壓力不小",
            "Vote": "推",
            "User": "Caramel0519"
        },
        {
            "Content": "主要是來自面子、朋友間互虧  那感覺不好受",
            "Vote": "→",
            "User": "Caramel0519"
        },
        {
            "Content": "雖然我們只是學生...Q_Q",
            "Vote": "→",
            "User": "Caramel0519"
        },
        {
            "Content": "我會開心  但是我有車了",
            "Vote": "推",
            "User": "easan"
        },
        {
            "Content": "可以當乘客是一件幸福的事情....  我都是司機 可以換人嗎?",
            "Vote": "推",
            "User": "u21054"
        },
        {
            "Content": "我男友一開始就不准我提開車的事,然後很老實的說他會沒面子.",
            "Vote": "推",
            "User": "Qmmmm"
        }
    ],
    [
        {
            "Content": "你誰啊，一直洗版",
            "Vote": "噓",
            "User": "c90051kevin"
        },
        {
            "Content": "我笑了  1F應該是今天新來的  真想轉到笨版  哈哈哈",
            "Vote": "推",
            "User": "pptbleu"
        },
        {
            "Content": "1F.....",
            "Vote": "→",
            "User": "hcy08200"
        },
        {
            "Content": "1f快跟版主檢舉阿!!!  XD",
            "Vote": "推",
            "User": "ppc"
        },
        {
            "Content": "為什麼總有這種分手後，不是還同進同出，互動舉止跟沒分",
            "Vote": "推",
            "User": "firstkiki"
        },
        {
            "Content": "這句話很傷人但....\"不是不想結婚，只是不想跟妳結婚\"",
            "Vote": "推",
            "User": "kenichisun"
        },
        {
            "Content": "他完全就是自私沒考慮到你",
            "Vote": "推",
            "User": "acetoluene"
        },
        {
            "Content": "因為牽扯到的東西太多了",
            "Vote": "→",
            "User": "sherlockt"
        },
        {
            "Content": "我不知道我回答的跟\"結婚跟戀愛、作愛等不能劃上等號\"",
            "Vote": "推",
            "User": "kenichisun"
        },
        {
            "Content": "到底是因為年齡還是錢的關係才急著結婚? 但他都說要放你走",
            "Vote": "→",
            "User": "houting"
        },
        {
            "Content": "既然如此為何還遲遲不肯殺出?",
            "Vote": "→",
            "User": "houting"
        },
        {
            "Content": "很痛的時候就去做想做的事.想哭就哭.發洩後會好過一點",
            "Vote": "→",
            "User": "abawemma"
        },
        {
            "Content": "我是覺得大概2~3個月後心情調適好一點可以安排一個小旅行",
            "Vote": "→",
            "User": "abawemma"
        },
        {
            "Content": "去花東走走看看.看海會讓心情變得平靜許多.試著跟自己獨",
            "Vote": "→",
            "User": "abawemma"
        },
        {
            "Content": "處.也試著讓自己過得比之前好.更亮眼.他若有一天回頭來看",
            "Vote": "→",
            "User": "abawemma"
        },
        {
            "Content": "你.發現你沒他卻過得更好.或許他才想起你的好.但那時你的",
            "Vote": "→",
            "User": "abawemma"
        },
        {
            "Content": "對象條件說不定都比他好.復合不難.難在復合後的相處.需要",
            "Vote": "→",
            "User": "abawemma"
        },
        {
            "Content": "更用心的付出.如果這段過程可以讓你對感情想法更成熟.要",
            "Vote": "→",
            "User": "abawemma"
        },
        {
            "Content": "找到一個可以過一輩子的人．應該會比想著這對象卻又擔心",
            "Vote": "→",
            "User": "abawemma"
        },
        {
            "Content": "這已經不是一廂情願，是一車了！！",
            "Vote": "推",
            "User": "Doraemi"
        },
        {
            "Content": "男友都說的很清楚了五年內不結婚 想結婚就得換人啊",
            "Vote": "→",
            "User": "autotroph"
        },
        {
            "Content": "31了，女人要更有目標而不是被他牽著走，妳漂亮何苦",
            "Vote": "推",
            "User": "chiachichen"
        },
        {
            "Content": "我看通常聰明的人不會因為女生鬧一鬧就昏頭結婚的",
            "Vote": "→",
            "User": "autotroph"
        },
        {
            "Content": "而且我男友也巨蟹，我天平，感覺巨蟹有點賤骨頭，不",
            "Vote": "推",
            "User": "chiachichen"
        },
        {
            "Content": "光看就覺得累,難怪他會跑",
            "Vote": "→",
            "User": "tsming"
        },
        {
            "Content": "光看就覺得跟你再一起好累，你想被照顧是你的問題不是別人",
            "Vote": "推",
            "User": "moerity"
        },
        {
            "Content": "理所當然要給你膠帶吧",
            "Vote": "→",
            "User": "moerity"
        },
        {
            "Content": "1F真的救了這篇                         排板很難嗎~~~",
            "Vote": "推",
            "User": "boyzone66"
        },
        {
            "Content": "既然來到BG版星座就不要提了吧　不然順便也附上血型",
            "Vote": "→",
            "User": "redspirit420"
        },
        {
            "Content": "為自己活 拜託",
            "Vote": "推",
            "User": "yiwei411219"
        },
        {
            "Content": "去找點事情做 忙到不再想到他 或是去相親轉移注意",
            "Vote": "→",
            "User": "CHRISTINAYEN"
        },
        {
            "Content": "他就是不想娶妳..身邊太多那種跟前女友長跑多年一分手再交",
            "Vote": "推",
            "User": "catkung"
        },
        {
            "Content": "下一個幾乎不到兩年就走入婚姻的例子了.算了吧",
            "Vote": "→",
            "User": "catkung"
        },
        {
            "Content": "男生不想結婚原因很多,不一定是女生的問題但女生吵會加速分手",
            "Vote": "→",
            "User": "ckin"
        },
        {
            "Content": "拍拍…你們對未來沒有共識，分開不見得不好，即使很痛",
            "Vote": "推",
            "User": "niceling"
        },
        {
            "Content": "為自己而活，找個愛你的人吧^^",
            "Vote": "→",
            "User": "niceling"
        },
        {
            "Content": "你在蟹版的文 我印象很深刻 當初不是蠻多人要你放棄嘛",
            "Vote": "推",
            "User": "lilychichi"
        },
        {
            "Content": "新男友跟妳交往還沒一年,就得為妳年紀到了負責喔?",
            "Vote": "→",
            "User": "dragonne"
        },
        {
            "Content": "交往四年,一年前開始逼婚,看錯了",
            "Vote": "→",
            "User": "dragonne"
        },
        {
            "Content": "先過好自己的生活，不要一味的配合他委曲求全，拍拍",
            "Vote": "→",
            "User": "ohm"
        }
    ],
    [
        {
            "Content": "1她已經不當你是男友了（確實也不是）只是你對她有情",
            "Vote": "推",
            "User": "neverlight"
        },
        {
            "Content": "那她就能繼續無痛享受你對她的好 超爽的 有權無責",
            "Vote": "→",
            "User": "neverlight"
        },
        {
            "Content": "舉個例子 男的分手了女的還愛男的繼續對男的負出",
            "Vote": "推",
            "User": "neverlight"
        },
        {
            "Content": "幫忙打掃家裡之類的 但卻只能眼睜睜看男的和別的女生",
            "Vote": "→",
            "User": "neverlight"
        },
        {
            "Content": "搞曖昧約會 卻也不能做什麼 只是＂朋友＂不是嗎？",
            "Vote": "→",
            "User": "neverlight"
        },
        {
            "Content": "女的期待男的會因為她的付出從新在一起",
            "Vote": "推",
            "User": "neverlight"
        },
        {
            "Content": "疏不知男的只當女的是免費佣人罷了",
            "Vote": "→",
            "User": "neverlight"
        },
        {
            "Content": "不要把薄弱關係的事情混在一起就能看清楚對方心態",
            "Vote": "→",
            "User": "diess"
        },
        {
            "Content": "最後對你說：不要為了一個不愛自己的人把自己搞糟",
            "Vote": "推",
            "User": "neverlight"
        },
        {
            "Content": "你自己也知道她不愛你了 繼續跟你互動或許是需要或慣性",
            "Vote": "→",
            "User": "neverlight"
        },
        {
            "Content": "但覺不是愛，想想愛你的爸媽，這一切值得嗎？",
            "Vote": "→",
            "User": "neverlight"
        },
        {
            "Content": "就不想跟你交往但還是想要你這個工具人啊",
            "Vote": "→",
            "User": "smallx3"
        },
        {
            "Content": "這種女生真的很.......最近才遇到= =",
            "Vote": "推",
            "User": "joh"
        },
        {
            "Content": "就被當工具人而已",
            "Vote": "推",
            "User": "iolo1166"
        },
        {
            "Content": ":) 謝謝關心",
            "Vote": "→",
            "User": "benkwok"
        },
        {
            "Content": "....你是M嗎??",
            "Vote": "→",
            "User": "bacon1989"
        },
        {
            "Content": "M ?什麼意思？",
            "Vote": "→",
            "User": "benkwok"
        }
    ],
    [
        {
            "Content": "學長還活著嗎?",
            "Vote": "→",
            "User": "tooth"
        },
        {
            "Content": "這是人的潛意識 也代表你真的有在想他 ( ￣ c￣)y▂ξ",
            "Vote": "推",
            "User": "Biantai"
        },
        {
            "Content": "不過幻想總是美麗的 現實總是殘酷的 拍拍",
            "Vote": "→",
            "User": "Biantai"
        }
    ],
    [
        {
            "Content": "我有類似的經驗，相信我塊陶啊！！！",
            "Vote": "推",
            "User": "Softrella"
        },
        {
            "Content": "-------------給其他男生一個機會吧-------------------",
            "Vote": "推",
            "User": "S9125126"
        },
        {
            "Content": "如果你每次都因為對方說得很好聽就交往，然後細數對方缺點",
            "Vote": "→",
            "User": "diess"
        },
        {
            "Content": "上板數落找分手認同，你的每一任都有可能是同樣下場",
            "Vote": "→",
            "User": "diess"
        },
        {
            "Content": "你太over了 這只是我的感受 分手認同？我只是迷路想找",
            "Vote": "→",
            "User": "jeslynlove"
        },
        {
            "Content": "個方向，你有事嗎?",
            "Vote": "→",
            "User": "jeslynlove"
        },
        {
            "Content": "覺得不適合就分手吧",
            "Vote": "推",
            "User": "by0413"
        },
        {
            "Content": "讓他莫名其妙被ban帳號 然後氣到發誓再也不玩LOL",
            "Vote": "→",
            "User": "takomalu"
        },
        {
            "Content": "晚上把你丟在路上也太誇張了= =那會整個讓人很心寒吧",
            "Vote": "推",
            "User": "kkemma"
        },
        {
            "Content": "ban帳號　還能創　lol等級很好練",
            "Vote": "→",
            "User": "kkemma"
        },
        {
            "Content": "才兩個月就這樣　那以後怎麼走下去呢？",
            "Vote": "→",
            "User": "kkemma"
        },
        {
            "Content": "這點程度就叫over？你的感受能力還真是無比的差",
            "Vote": "→",
            "User": "diess"
        },
        {
            "Content": "當初交往時因為感受，交往後也因為感受，那請問何時輪到你的",
            "Vote": "→",
            "User": "diess"
        },
        {
            "Content": "理智來判斷？若每次交往都只用感受來負責，是不是就要經常性",
            "Vote": "→",
            "User": "diess"
        },
        {
            "Content": "迷路來這裡，不否認這男的很差，但你自己是否有從這失敗中",
            "Vote": "→",
            "User": "diess"
        },
        {
            "Content": "到底是怎麼判斷出這些問題的主因是LOL的阿?? 特異功能?",
            "Vote": "→",
            "User": "GoodFriday"
        },
        {
            "Content": "找出真正的原因？不是因為對方會講好聽話就交往",
            "Vote": "→",
            "User": "diess"
        },
        {
            "Content": "也不是短短兩個月發現對方不如期待就細數罪狀找分手認同",
            "Vote": "→",
            "User": "diess"
        },
        {
            "Content": "分手只要你想分就可以，就算對方是大家眼中天大好男人",
            "Vote": "→",
            "User": "diess"
        },
        {
            "Content": "你無法適應跟他一起的生活就分手也沒有錯，只是你要多動動腦",
            "Vote": "→",
            "User": "diess"
        },
        {
            "Content": "不是一句「我的感受」就不用認真去思考一切，去敵視所有人",
            "Vote": "→",
            "User": "diess"
        },
        {
            "Content": "還有，別忘了，起先是男友對你「玩遊戲」很生氣",
            "Vote": "→",
            "User": "diess"
        },
        {
            "Content": "這段你可是非常地輕描淡寫，然後換他玩遊戲後就變成你嫌他",
            "Vote": "→",
            "User": "diess"
        },
        {
            "Content": "不體貼然後一一細數對方的罪狀，兩邊的量可是差異很大",
            "Vote": "→",
            "User": "diess"
        },
        {
            "Content": "他只是想比妳強。",
            "Vote": "推",
            "User": "scufjh"
        },
        {
            "Content": "可能他玩AD遇到喜歡的SPU吧   男人都脫離不了新鮮感的",
            "Vote": "推",
            "User": "namcp"
        },
        {
            "Content": "兩個月就這樣物來也沒辦法對你更好  分了吧   兩個月還在熱",
            "Vote": "→",
            "User": "namcp"
        },
        {
            "Content": "ㄏㄏ，什麼人不嗆，嗆diess大大",
            "Vote": "推",
            "User": "hiyida"
        },
        {
            "Content": "SPU是什麼鬼",
            "Vote": "推",
            "User": "CaOH2"
        },
        {
            "Content": "抱歉單手打字沒選字打錯字  是SUP~",
            "Vote": "推",
            "User": "namcp"
        },
        {
            "Content": "除了1可能和妳標題有點關係之外 其他幾點的關係是?",
            "Vote": "→",
            "User": "se493671"
        },
        {
            "Content": "zzz，自己掉頭走掉還奢求別人回頭攔你，偶像劇吧",
            "Vote": "→",
            "User": "a28829424"
        },
        {
            "Content": "公主駕到~~",
            "Vote": "推",
            "User": "z0779"
        },
        {
            "Content": "妳塊陶阿~~~~這種男人不要也罷",
            "Vote": "推",
            "User": "moki"
        },
        {
            "Content": "WOW 某D以前不是被打臉打的很兇 一陣子不見變大大了",
            "Vote": "噓",
            "User": "gogomanX"
        },
        {
            "Content": "直接攤開來講吧 大家都成年人了 沒什麼不能溝通的",
            "Vote": "推",
            "User": "acetoluene"
        },
        {
            "Content": "沒必要自以為正義還揣測po文的心態吧？",
            "Vote": "推",
            "User": "shark157"
        },
        {
            "Content": "怎不來點具體可行的意見？BG版都這樣被弄臭的",
            "Vote": "→",
            "User": "shark157"
        }
    ]
]